{"ticker": "CTRA", "fiscal_quarter_end": "2023-03-31", "decision_date_T": "2023-04-20", "n_pads_sampled": 25, "n_newly_active": 3, "n_continuously_active": 2, "n_idle": 20, "n_observations_total": 1926, "pad_classifications": [{"pad_id": "30015491700000", "lat": 32.664452, "lon": -104.07365, "n_obs": 86, "classification": "idle"}, {"pad_id": "30015455500000", "lat": 32.665094, "lon": -104.068956, "n_obs": 86, "classification": "idle"}, {"pad_id": "30015431730000", "lat": 32.003056, "lon": -104.1699, "n_obs": 58, "classification": "idle"}, {"pad_id": "30015491970000", "lat": 32.664342, "lon": -104.070364, "n_obs": 86, "classification": "idle"}, {"pad_id": "30015463350000", "lat": 32.665094, "lon": -104.06895, "n_obs": 86, "classification": "idle"}, {"pad_id": "30015433730000", "lat": 32.1814, "lon": -104.2482, "n_obs": 58, "classification": "idle"}, {"pad_id": "30025050750000", "lat": 32.09341, "lon": -103.595607, "n_obs": 86, "classification": "idle"}, {"pad_id": "30015465600000", "lat": 32.0221, "lon": -103.9281, "n_obs": 86, "classification": "idle"}, {"pad_id": "30015433770000", "lat": 32.181292, "lon": -104.247619, "n_obs": 58, "classification": "idle"}, {"pad_id": "30025463180000", "lat": 32.2386, "lon": -103.6357, "n_obs": 86, "classification": "newly_active"}, {"pad_id": "30015465610000", "lat": 32.0221, "lon": -103.9279, "n_obs": 86, "classification": "idle"}, {"pad_id": "30015446950000", "lat": 32.150658, "lon": -104.225014, "n_obs": 58, "classification": "idle"}, {"pad_id": "30025463190000", "lat": 32.238754, "lon": -103.631578, "n_obs": 86, "classification": "continuously_active"}, {"pad_id": "30015465620000", "lat": 32.0221, "lon": -103.92791, "n_obs": 86, "classification": "idle"}, {"pad_id": "30015447900000", "lat": 32.150658, "lon": -104.225078, "n_obs": 58, "classification": "idle"}, {"pad_id": "30025463210000", "lat": 32.2386, "lon": -103.6358, "n_obs": 86, "classification": "newly_active"}, {"pad_id": "30015465670000", "lat": 32.0226, "lon": -103.9245, "n_obs": 86, "classification": "idle"}, {"pad_id": "30015451470000", "lat": 32.120136, "lon": -104.218878, "n_obs": 58, "classification": "idle"}, {"pad_id": "30025463220000", "lat": 32.238754, "lon": -103.631642, "n_obs": 86, "classification": "continuously_active"}, {"pad_id": "30015465680000", "lat": 32.0225, "lon": -103.9245, "n_obs": 86, "classification": "idle"}, {"pad_id": "30015451480000", "lat": 32.120079, "lon": -104.218761, "n_obs": 58, "classification": "idle"}, {"pad_id": "30025501350000", "lat": 32.2385, "lon": -103.6357, "n_obs": 86, "classification": "newly_active"}, {"pad_id": "30015465700000", "lat": 32.0226, "lon": -103.9246, "n_obs": 86, "classification": "idle"}, {"pad_id": "30015452650000", "lat": 32.152888, "lon": -104.222018, "n_obs": 58, "classification": "idle"}, {"pad_id": "30025502070000", "lat": 32.093413, "lon": -103.601467, "n_obs": 86, "classification": "idle"}]}