{"ticker": "OXY", "fiscal_quarter_end": "2021-09-30", "decision_date_T": "2021-10-21", "n_pads_sampled": 5, "n_newly_active": 1, "n_continuously_active": 4, "n_idle": 0, "n_observations_total": 426, "pad_classifications": [{"pad_id": "30015479720000", "lat": 32.213097, "lon": -104.000639, "n_obs": 91, "classification": "continuously_active"}, {"pad_id": "30015408210000", "lat": 32.399651, "lon": -103.724258, "n_obs": 91, "classification": "continuously_active"}, {"pad_id": "30015431230000", "lat": 32.579641, "lon": -104.140281, "n_obs": 62, "classification": "newly_active"}, {"pad_id": "30015479740000", "lat": 32.213096, "lon": -104.000525, "n_obs": 91, "classification": "continuously_active"}, {"pad_id": "30015415960000", "lat": 32.222065, "lon": -103.981995, "n_obs": 91, "classification": "continuously_active"}]}